{"card_name": "The Path of War", "color": "R", "rarity": "rare", "type": "Legendary Enchantment", "number": 155, "color_identity": "R", "cost": "{3}{R}", "rules_text": "Whenever you attack, add {R} for each attacking creature. Until end of turn, you don\u2019t lose this mana as steps and phases end.\nWhenever you expend 15, put a domination counter on this enchantment.\nAt the beginning of your upkeep, if this enchantment has a domination counter on it, you win the game.", "pt": "", "special_text": "", "shape": "normal", "set": "DWE", "loyalty": "", "notes": "Wincon cycle", "image_type": "png"}