{"card_name": "Summoner's Volute", "color": "G", "rarity": "rare", "type": "Enchantment \u2013 Aura", "number": 50, "color_identity": "G", "cost": "{2}{G}{G}", "rules_text": "Enchant card in your hand\nAt the beginning of your upkeep, you may reveal the enchanted card. If it\u2019s a creature card, you may sacrifice Summoner\u2019s Volute and put that card onto the battlefield.", "pt": "", "special_text": "", "shape": "normal", "set": "MYC", "loyalty": "", "notes": "Inspiration \u2014 Ancient/Cursed Scroll, Summoning Incantation\n\nMechanical Uniqueness \u2014 Enchanting a card not on the battlefield.", "image_type": "png"}