{"card_name": "Effa, Verdurous Critic", "color": "G", "rarity": "rare", "type": "Legendary Creature \u2013 Elf Advisor", "number": 184, "color_identity": "G", "cost": "{2}{G}{G}", "rules_text": "When Effa, Verdurous Critic enters, put a +1/+1 counter on target creature you control.\nWhenever you attack, double the power of up to one target creature with a counter on it until end of turn.", "pt": "3/3", "special_text": "", "shape": "normal", "set": "CHF", "loyalty": "", "notes": "New card \u2014 Replaced Porridge Ooze\n\nWith the Oozes having been reworked, this slot opened up to make room for the legendary judges cycle.", "image_type": "png"}