{"card_name": "Gigantifier Jelly", "color": "G", "rarity": "rare", "type": "Creature \u2013 Ooze", "number": 187, "color_identity": "G", "cost": "{G}", "rules_text": "Reach, trample, vigilance\nDecompose into X/X green Ooze creature {X}{G}{G} [i]({X}{G}{G}, Exile this card from your graveyard: Create a token that\u2019s a copy of it, except it\u2019s an X/X green Ooze creature with no mana cost and it loses all other card types. Decompose only as a sorcery.)[/i]", "pt": "1/1", "special_text": "", "shape": "normal", "set": "CHF", "loyalty": "", "notes": "New card \u2014 Replaced Nourishing Hydra\n\nThese two were doing very similar things, and since Jelly shows off a novel usage of Decompose, and there\u2019s another nourish rare in green, this seemed like a good swap.", "image_type": "png"}