{"card_name": "Foodie Family", "color": "WG", "rarity": "uncommon", "type": "Creature \u2013 Human Chef", "number": 214, "color_identity": "WG", "cost": "{1}{G}{W}", "rules_text": "When Foodie Family enters, create a Food token. [i](It\u2019s an artifact with \u201c{2}, {T}, Sacrifice this artifact: You gain 3 life.\u201d)[/i]\nWhenever one or more Foods enter under your control, put a +1/+1 counter on target creature you control.", "pt": "2/2", "special_text": "", "shape": "normal", "set": "CHF", "loyalty": "", "notes": "Added name, added art\nReworked entirely", "image_type": "png"}