{"card_name": "Ambidextrous Spellcook", "color": "U", "rarity": "common", "type": "Creature \u2013 Octopus Wizard Chef", "number": 53, "color_identity": "U", "cost": "{2}{U}", "rules_text": "Prowess [i](Whenever you cast a noncreature spell, this creature gets +1/+1 until end of turn.)[/i]\nWhen Ambidextrous Spellcook enters, you may draw a card. If you do, discard a card.", "pt": "2/2", "special_text": "", "shape": "normal", "set": "CHF", "loyalty": "", "notes": "Changed name, added art, added flavor text\nCephalid \u2014> Octopus", "image_type": "png"}