{"card_name": "Check Please", "color": "U", "rarity": "common", "type": "Instant", "number": 64, "color_identity": "U", "cost": "{1}{U}", "rules_text": "Counter target spell unless its controller pays {X}, where X is 1 plus the number of artifacts you control.", "pt": "", "special_text": "", "shape": "normal", "set": "CHF", "loyalty": "", "notes": "Changed flavor text slightly\n\nChanged X from 2 + artifacts to 1 + artifacts to make the floor a bit lower than quench, given the cieling can be much higher", "image_type": "png"}